scratch_3_file_analyser/__init__.py
scratch_3_file_analyser-0.1.1a0.dist-info/LICENSE
scratch_3_file_analyser-0.1.1a0.dist-info/METADATA
scratch_3_file_analyser-0.1.1a0.dist-info/WHEEL
scratch_3_file_analyser-0.1.1a0.dist-info/top_level.txt
scratch_3_file_analyser-0.1.1a0.dist-info/RECORD
