Metadata-Version: 2.1
Name: scratch-3-file-analyser
Version: 0.1.1.alpha
Summary: A analyzer for Scratch3 files
Home-page: https://github.com/A-bear-eating-books/scratch_3_file_analyser
Author: chishudexiong
Author-email: 2326311571@qq.com
License: UNKNOWN
Platform: UNKNOWN
Classifier: Programming Language :: Python :: 3.10
Classifier: Development Status :: 3 - Alpha
Classifier: License :: OSI Approved :: GNU General Public License v3 or later (GPLv3+)
Classifier: Natural Language :: Chinese (Simplified)
License-File: LICENSE
